annoPipeline/__init__.py
annoPipeline/addBibs.py
annoPipeline/getAnno.py
annoPipeline/queryGenes.py
test/__init__.py
annoPipeline-0.0.1.dist-info/LICENSE.txt
annoPipeline-0.0.1.dist-info/METADATA
annoPipeline-0.0.1.dist-info/WHEEL
annoPipeline-0.0.1.dist-info/top_level.txt
annoPipeline-0.0.1.dist-info/RECORD
