Metadata-Version: 2.1
Name: annoPipeline
Version: 0.0.1
Summary: API-enabled Gene Annotation
Home-page: https://github.com/jimmyjamesarnold/annoPipeline
Author: Jim Arnold
Author-email: jimmyjamesarnold@gmail.com
License: MIT
Platform: UNKNOWN
Classifier: Development Status :: 3 - Alpha
Classifier: Intended Audience :: Science/Research
Classifier: License :: OSI Approved :: MIT License
Classifier: Programming Language :: Python :: 3
Classifier: Operating System :: OS Independent
Classifier: Topic :: Scientific/Engineering :: Information Analysis
Classifier: Topic :: Scientific/Engineering :: Interface Engine/Protocol Translator
Requires-Dist: numpy (>=1.16.2)
Requires-Dist: pandas (>=0.24.2)
Requires-Dist: Biopython (>=1.73)
Requires-Dist: openpyxl (>=2.6.1)
Requires-Dist: requests (>=2.21.0)
